lazydev/__init__.py
lazydev/develop.py
lazydev/modules/__init__.py
lazydev/modules/developer.py
lazydev/modules/prompts.py
lazydev/modules/utils.py
lazydev-0.1.3.dist-info/LICENSE
lazydev-0.1.3.dist-info/METADATA
lazydev-0.1.3.dist-info/WHEEL
lazydev-0.1.3.dist-info/entry_points.txt
lazydev-0.1.3.dist-info/top_level.txt
lazydev-0.1.3.dist-info/RECORD
