Metadata-Version: 2.1
Name: lazydev
Version: 0.1.3
Summary: AI developer for lazy programmer
Home-page: https://github.com/thecodacus/lazy-dev
Author: Anirban Kat
Author-email: thecodacus@gmail.com
Classifier: Development Status :: 5 - Production/Stable
Classifier: Intended Audience :: Developers
Classifier: License :: OSI Approved :: Apache Software License
Classifier: Operating System :: OS Independent
Classifier: Programming Language :: Python :: 3
Classifier: Programming Language :: Python :: 3.8
Classifier: Programming Language :: Python :: 3.9
Classifier: Programming Language :: Python :: 3.10
License-File: LICENSE
Requires-Dist: langchain>=0.0.188
Requires-Dist: openai>=0.27.7
